LICENSE
MANIFEST.in
README.md
setup.py
src/filebrowser_upload/__init__.py
src/filebrowser_upload/__version__.py
src/filebrowser_upload/main.py
src/filebrowser_upload.egg-info/PKG-INFO
src/filebrowser_upload.egg-info/SOURCES.txt
src/filebrowser_upload.egg-info/dependency_links.txt
src/filebrowser_upload.egg-info/entry_points.txt
src/filebrowser_upload.egg-info/top_level.txt
src/filebrowser_upload/vendor/certifi/__init__.py
src/filebrowser_upload/vendor/certifi/__main__.py
src/filebrowser_upload/vendor/certifi/cacert.pem
src/filebrowser_upload/vendor/certifi/core.py
src/filebrowser_upload/vendor/chardet/__init__.py
src/filebrowser_upload/vendor/chardet/big5freq.py
src/filebrowser_upload/vendor/chardet/big5prober.py
src/filebrowser_upload/vendor/chardet/chardistribution.py
src/filebrowser_upload/vendor/chardet/charsetgroupprober.py
src/filebrowser_upload/vendor/chardet/charsetprober.py
src/filebrowser_upload/vendor/chardet/codingstatemachine.py
src/filebrowser_upload/vendor/chardet/compat.py
src/filebrowser_upload/vendor/chardet/cp949prober.py
src/filebrowser_upload/vendor/chardet/enums.py
src/filebrowser_upload/vendor/chardet/escprober.py
src/filebrowser_upload/vendor/chardet/escsm.py
src/filebrowser_upload/vendor/chardet/eucjpprober.py
src/filebrowser_upload/vendor/chardet/euckrfreq.py
src/filebrowser_upload/vendor/chardet/euckrprober.py
src/filebrowser_upload/vendor/chardet/euctwfreq.py
src/filebrowser_upload/vendor/chardet/euctwprober.py
src/filebrowser_upload/vendor/chardet/gb2312freq.py
src/filebrowser_upload/vendor/chardet/gb2312prober.py
src/filebrowser_upload/vendor/chardet/hebrewprober.py
src/filebrowser_upload/vendor/chardet/jisfreq.py
src/filebrowser_upload/vendor/chardet/jpcntx.py
src/filebrowser_upload/vendor/chardet/langbulgarianmodel.py
src/filebrowser_upload/vendor/chardet/langcyrillicmodel.py
src/filebrowser_upload/vendor/chardet/langgreekmodel.py
src/filebrowser_upload/vendor/chardet/langhebrewmodel.py
src/filebrowser_upload/vendor/chardet/langhungarianmodel.py
src/filebrowser_upload/vendor/chardet/langthaimodel.py
src/filebrowser_upload/vendor/chardet/langturkishmodel.py
src/filebrowser_upload/vendor/chardet/latin1prober.py
