Metadata-Version: 1.1
Name: filebrowser-upload
Version: 0.3.0
Summary: Watch PATH and rsync to DEST
Home-page: https://github.com/guyskk/filebrowser-upload
Author: guyskk
Author-email: guyskk@qq.com
License: MIT
Platform: UNKNOWN
Classifier: Development Status :: 5 - Production/Stable
Classifier: Environment :: Console
Classifier: Intended Audience :: Developers
Classifier: Intended Audience :: System Administrators
Classifier: License :: OSI Approved :: MIT License
Classifier: Operating System :: MacOS :: MacOS X
Classifier: Operating System :: POSIX
Classifier: Programming Language :: Python
